unsloth_env_test_wjz718/__init__.py
unsloth_env_test_wjz718-0.1.2.dist-info/licenses/LICENSE
unsloth_env_test_wjz718-0.1.2.dist-info/WHEEL
unsloth_env_test_wjz718-0.1.2.dist-info/METADATA
unsloth_env_test_wjz718-0.1.2.dist-info/RECORD
