Metadata-Version: 2.4
Name: unsloth_env_test_wjz718
Version: 0.1.2
Summary: unsloth_env_test_wjz718 - A minimal PyPI package example.
Author-email: wjz718 <2980376403@qq.com>
License-Expression: MIT
License-File: LICENSE
